 0.0% done, time left: unknown                                0.4% done, time left: unknown  0.7% done, time left: unknown  1.7% done, time left: unknown  2.9% done, time left: unknown  3.0% done, time left: unknown  3.6% done, time left: unknown  6.0% done, time left:   0:00:04    8.5% done, time left:   0:00:04  8.5% done, time left:   0:00:05  8.5% done, time left:   0:00:06  8.5% done, time left:   0:00:07  8.5% done, time left:   0:00:08  8.5% done, time left:   0:00:09  8.5% done, time left:   0:00:10  8.5% done, time left:   0:00:11 10.3% done, time left:   0:00:13 14.0% done, time left:   0:00:10 16.3% done, time left:   0:00:08 16.3% done, time left:   0:00:06 16.3% done, time left:   0:00:04 16.3% done, time left:   0:00:03 16.3% done, time left:   0:00:02 16.3% done, time left:   0:00:01 16.3% done, time left:   0:00:02 17.7% done, time left:   0:00:04 18.9% done, time left:   0:00:05 23.1% done, time left:   0:00:04 27.6% done, time left:   0:00:03 28.6% done, time left:   0:00:01 28.6% done, time left:   0:00:00 35.3% done, time left:   0:00:00 40.1% done, time left:   0:00:01 44.8% done, time left:   0:00:01 49.6% done, time left:   0:00:01 51.6% done, time left:   0:00:00 54.0% done, time left:   0:00:00 56.6% done, time left:   0:00:01 58.8% done, time left:   0:00:01 58.8% done, time left:   0:00:00 59.1% done, time left:   0:00:00 61.0% done, time left:   0:00:00 65.0% done, time left:   0:00:00 68.4% done, time left:   0:00:00 70.6% done, time left:   0:00:00 72.3% done, time left:   0:00:00 74.7% done, time left:   0:00:00 75.7% done, time left:   0:00:00 76.3% done, time left:   0:00:00 76.8% done, time left:   0:00:00 78.7% done, time left:   0:00:00 83.5% done, time left:   0:00:00 85.9% done, time left:   0:00:00 87.3% done, time left:   0:00:00 88.8% done, time left:   0:00:00 89.8% done, time left:   0:00:00 90.1% done, time left:   0:00:00 90.9% done, time left:   0:00:00 93.9% done, time left:   0:00:00 99.1% done, time left:   0:00:00 99.6% done, time left:   0:00:00 100.0% done, time left:   0:00:00  finished
The dynamic slice for criterion [org.apache.commons.lang3.ConversionTest.testUuidToByteArray:1828:*]:
org.apache.commons.lang3.Conversion.uuidToByteArray:1533 ICONST_0
org.apache.commons.lang3.Conversion.uuidToByteArray:1533 ILOAD 3
org.apache.commons.lang3.Conversion.uuidToByteArray:1533 IF_ICMPNE L0 true false
org.apache.commons.lang3.Conversion.uuidToByteArray:1543 ALOAD 1
org.apache.commons.lang3.Conversion.uuidToByteArray:1543 ARETURN
org.apache.commons.lang3.ConversionTest.main:81 INVOKEVIRTUAL org/apache/commons/lang3/ConversionTest.testUuidToByteArray()V
org.apache.commons.lang3.ConversionTest.testUuidToByteArray:1823 BIPUSH 16
org.apache.commons.lang3.ConversionTest.testUuidToByteArray:1828 BIPUSH 16
org.apache.commons.lang3.ConversionTest.testUuidToByteArray:1828 NEWARRAY T_BYTE
org.apache.commons.lang3.ConversionTest.testUuidToByteArray:1828 DUP
org.apache.commons.lang3.ConversionTest.testUuidToByteArray:1828 ICONST_0
org.apache.commons.lang3.ConversionTest.testUuidToByteArray:1828 BIPUSH -120
org.apache.commons.lang3.ConversionTest.testUuidToByteArray:1828 BASTORE
org.apache.commons.lang3.ConversionTest.testUuidToByteArray:1828 DUP
org.apache.commons.lang3.ConversionTest.testUuidToByteArray:1828 ICONST_1
org.apache.commons.lang3.ConversionTest.testUuidToByteArray:1828 BIPUSH -103
org.apache.commons.lang3.ConversionTest.testUuidToByteArray:1828 BASTORE
org.apache.commons.lang3.ConversionTest.testUuidToByteArray:1828 DUP
org.apache.commons.lang3.ConversionTest.testUuidToByteArray:1828 ICONST_2
org.apache.commons.lang3.ConversionTest.testUuidToByteArray:1828 BIPUSH -86
org.apache.commons.lang3.ConversionTest.testUuidToByteArray:1828 BASTORE
org.apache.commons.lang3.ConversionTest.testUuidToByteArray:1828 DUP
org.apache.commons.lang3.ConversionTest.testUuidToByteArray:1828 ICONST_3
org.apache.commons.lang3.ConversionTest.testUuidToByteArray:1828 BIPUSH -69
org.apache.commons.lang3.ConversionTest.testUuidToByteArray:1828 BASTORE
org.apache.commons.lang3.ConversionTest.testUuidToByteArray:1828 DUP
org.apache.commons.lang3.ConversionTest.testUuidToByteArray:1828 ICONST_4
org.apache.commons.lang3.ConversionTest.testUuidToByteArray:1828 BIPUSH -52
org.apache.commons.lang3.ConversionTest.testUuidToByteArray:1828 BASTORE
org.apache.commons.lang3.ConversionTest.testUuidToByteArray:1828 DUP
org.apache.commons.lang3.ConversionTest.testUuidToByteArray:1828 ICONST_5
org.apache.commons.lang3.ConversionTest.testUuidToByteArray:1828 BIPUSH -35
org.apache.commons.lang3.ConversionTest.testUuidToByteArray:1828 BASTORE
org.apache.commons.lang3.ConversionTest.testUuidToByteArray:1828 DUP
org.apache.commons.lang3.ConversionTest.testUuidToByteArray:1828 BIPUSH 6
org.apache.commons.lang3.ConversionTest.testUuidToByteArray:1828 BIPUSH -18
org.apache.commons.lang3.ConversionTest.testUuidToByteArray:1828 BASTORE
org.apache.commons.lang3.ConversionTest.testUuidToByteArray:1828 DUP
org.apache.commons.lang3.ConversionTest.testUuidToByteArray:1828 BIPUSH 7
org.apache.commons.lang3.ConversionTest.testUuidToByteArray:1828 ICONST_M1
org.apache.commons.lang3.ConversionTest.testUuidToByteArray:1828 BASTORE
org.apache.commons.lang3.ConversionTest.testUuidToByteArray:1828 DUP
org.apache.commons.lang3.ConversionTest.testUuidToByteArray:1828 BIPUSH 8
org.apache.commons.lang3.ConversionTest.testUuidToByteArray:1828 ICONST_0
org.apache.commons.lang3.ConversionTest.testUuidToByteArray:1828 BASTORE
org.apache.commons.lang3.ConversionTest.testUuidToByteArray:1828 DUP
org.apache.commons.lang3.ConversionTest.testUuidToByteArray:1828 BIPUSH 9
org.apache.commons.lang3.ConversionTest.testUuidToByteArray:1828 BIPUSH 17
org.apache.commons.lang3.ConversionTest.testUuidToByteArray:1828 BASTORE
org.apache.commons.lang3.ConversionTest.testUuidToByteArray:1828 DUP
org.apache.commons.lang3.ConversionTest.testUuidToByteArray:1828 BIPUSH 10
org.apache.commons.lang3.ConversionTest.testUuidToByteArray:1828 BIPUSH 34
org.apache.commons.lang3.ConversionTest.testUuidToByteArray:1828 BASTORE
org.apache.commons.lang3.ConversionTest.testUuidToByteArray:1828 DUP
org.apache.commons.lang3.ConversionTest.testUuidToByteArray:1828 BIPUSH 11
org.apache.commons.lang3.ConversionTest.testUuidToByteArray:1828 BIPUSH 51
org.apache.commons.lang3.ConversionTest.testUuidToByteArray:1828 BASTORE
org.apache.commons.lang3.ConversionTest.testUuidToByteArray:1828 DUP
org.apache.commons.lang3.ConversionTest.testUuidToByteArray:1828 BIPUSH 12
org.apache.commons.lang3.ConversionTest.testUuidToByteArray:1828 BIPUSH 68
org.apache.commons.lang3.ConversionTest.testUuidToByteArray:1828 BASTORE
org.apache.commons.lang3.ConversionTest.testUuidToByteArray:1828 DUP
org.apache.commons.lang3.ConversionTest.testUuidToByteArray:1828 BIPUSH 13
org.apache.commons.lang3.ConversionTest.testUuidToByteArray:1828 BIPUSH 85
org.apache.commons.lang3.ConversionTest.testUuidToByteArray:1828 BASTORE
org.apache.commons.lang3.ConversionTest.testUuidToByteArray:1828 DUP
org.apache.commons.lang3.ConversionTest.testUuidToByteArray:1828 BIPUSH 14
org.apache.commons.lang3.ConversionTest.testUuidToByteArray:1828 BIPUSH 102
org.apache.commons.lang3.ConversionTest.testUuidToByteArray:1828 BASTORE
org.apache.commons.lang3.ConversionTest.testUuidToByteArray:1828 DUP
org.apache.commons.lang3.ConversionTest.testUuidToByteArray:1828 BIPUSH 15
org.apache.commons.lang3.ConversionTest.testUuidToByteArray:1828 BIPUSH 119
org.apache.commons.lang3.ConversionTest.testUuidToByteArray:1828 BASTORE
org.apache.commons.lang3.ConversionTest.testUuidToByteArray:1828 NEW java/util/UUID
org.apache.commons.lang3.ConversionTest.testUuidToByteArray:1828 DUP
org.apache.commons.lang3.ConversionTest.testUuidToByteArray:1828 LDC -4822678189205112
org.apache.commons.lang3.ConversionTest.testUuidToByteArray:1828 LDC 8603657889541918976
org.apache.commons.lang3.ConversionTest.testUuidToByteArray:1828 INVOKESPECIAL java/util/UUID.<init>(JJ)V
org.apache.commons.lang3.ConversionTest.testUuidToByteArray:1828 BIPUSH 16
org.apache.commons.lang3.ConversionTest.testUuidToByteArray:1828 NEWARRAY T_BYTE
org.apache.commons.lang3.ConversionTest.testUuidToByteArray:1828 ICONST_0
org.apache.commons.lang3.ConversionTest.testUuidToByteArray:1828 BIPUSH 16
org.apache.commons.lang3.ConversionTest.testUuidToByteArray:1828 INVOKESTATIC org/apache/commons/lang3/Conversion.uuidToByteArray(Ljava/util/UUID;[BII)[B
org.apache.commons.lang3.ConversionTest.testUuidToByteArray:1828 INVOKESTATIC org/junit/Assert.assertArrayEquals([B[B)V

Slice consists of 84 bytecode instructions.
Computation took 25.93 seconds.
