 0.0% done, time left: unknown                                0.1% done, time left: unknown  0.3% done, time left: unknown  0.4% done, time left: unknown  0.5% done, time left:   0:04:16    0.5% done, time left:   0:06:07  0.5% done, time left:   0:06:12  0.5% done, time left:   0:06:47  0.5% done, time left:   0:07:33  0.5% done, time left:   0:08:25  0.5% done, time left:   0:09:20  0.6% done, time left:   0:08:54  0.8% done, time left:   0:08:20  1.1% done, time left:   0:07:46  1.2% done, time left:   0:07:16  1.4% done, time left:   0:06:49  1.7% done, time left:   0:06:26  2.1% done, time left:   0:06:04  2.3% done, time left:   0:05:45  2.6% done, time left:   0:05:28  2.8% done, time left:   0:05:13  3.3% done, time left:   0:05:01  3.7% done, time left:   0:04:50  4.3% done, time left:   0:04:40  4.9% done, time left:   0:04:30  5.5% done, time left:   0:04:21  6.1% done, time left:   0:04:13  6.6% done, time left:   0:04:05  7.2% done, time left:   0:03:58  7.8% done, time left:   0:03:50  8.3% done, time left:   0:03:41  8.9% done, time left:   0:03:33  9.2% done, time left:   0:03:24  9.9% done, time left:   0:03:16 10.6% done, time left:   0:03:07 11.2% done, time left:   0:02:59 12.1% done, time left:   0:02:50 12.8% done, time left:   0:02:40 13.5% done, time left:   0:02:31 14.1% done, time left:   0:02:22 14.9% done, time left:   0:02:14 15.7% done, time left:   0:02:05 16.5% done, time left:   0:01:57 17.3% done, time left:   0:01:49 18.8% done, time left:   0:01:42 20.5% done, time left:   0:01:31 23.6% done, time left:   0:01:05 25.1% done, time left:   0:00:48 25.1% done, time left:   0:00:35 25.1% done, time left:   0:00:25 25.7% done, time left:   0:00:20 26.8% done, time left:   0:00:16 28.2% done, time left:   0:00:14 28.2% done, time left:   0:00:11 28.8% done, time left:   0:00:09 31.5% done, time left:   0:00:10 32.3% done, time left:   0:00:09 35.0% done, time left:   0:00:08 38.1% done, time left:   0:00:06 40.6% done, time left:   0:00:04 41.9% done, time left:   0:00:03 45.0% done, time left:   0:00:02 46.7% done, time left:   0:00:02 50.3% done, time left:   0:00:01 52.6% done, time left:   0:00:01 52.7% done, time left:   0:00:00 56.0% done, time left:   0:00:01 59.1% done, time left:   0:00:01 62.6% done, time left:   0:00:00 65.9% done, time left:   0:00:00 66.6% done, time left:   0:00:00 69.7% done, time left:   0:00:00 72.7% done, time left:   0:00:00 75.3% done, time left:   0:00:00 78.5% done, time left:   0:00:00 81.7% done, time left:   0:00:00 84.7% done, time left:   0:00:00 88.2% done, time left:   0:00:00 91.4% done, time left:   0:00:00 94.4% done, time left:   0:00:00 96.4% done, time left:   0:00:00 99.2% done, time left:   0:00:00 100.0% done, time left:   0:00:00  finished
The dynamic slice for criterion [org.apache.commons.codec.digest.XXHash32Test.verifyChecksum:76:*]:
org.apache.commons.codec.digest.XXHash32.<init>:45 ALOAD 0
org.apache.commons.codec.digest.XXHash32.<init>:45 ICONST_4
org.apache.commons.codec.digest.XXHash32.<init>:45 NEWARRAY T_INT
org.apache.commons.codec.digest.XXHash32.<init>:45 PUTFIELD org/apache/commons/codec/digest/XXHash32.state [I
org.apache.commons.codec.digest.XXHash32.<init>:58 ALOAD 0
org.apache.commons.codec.digest.XXHash32.<init>:58 ICONST_0
org.apache.commons.codec.digest.XXHash32.<init>:58 INVOKESPECIAL org/apache/commons/codec/digest/XXHash32.<init>(I)V
org.apache.commons.codec.digest.XXHash32.<init>:66 ALOAD 0
org.apache.commons.codec.digest.XXHash32.<init>:66 ILOAD 1
org.apache.commons.codec.digest.XXHash32.<init>:66 PUTFIELD org/apache/commons/codec/digest/XXHash32.seed I
org.apache.commons.codec.digest.XXHash32.<init>:67 ALOAD 0
org.apache.commons.codec.digest.XXHash32.<init>:67 INVOKESPECIAL org/apache/commons/codec/digest/XXHash32.initializeState()V
org.apache.commons.codec.digest.XXHash32.update:85 ILOAD 3
org.apache.commons.codec.digest.XXHash32.update:85 IFGT L0 true false
org.apache.commons.codec.digest.XXHash32.update:88 ALOAD 0
org.apache.commons.codec.digest.XXHash32.update:88 DUP
org.apache.commons.codec.digest.XXHash32.update:88 GETFIELD org/apache/commons/codec/digest/XXHash32.totalLen I
org.apache.commons.codec.digest.XXHash32.update:88 ILOAD 3
org.apache.commons.codec.digest.XXHash32.update:88 IADD
org.apache.commons.codec.digest.XXHash32.update:88 PUTFIELD org/apache/commons/codec/digest/XXHash32.totalLen I
org.apache.commons.codec.digest.XXHash32.update:90 ILOAD 2
org.apache.commons.codec.digest.XXHash32.update:90 ILOAD 3
org.apache.commons.codec.digest.XXHash32.update:90 IADD
org.apache.commons.codec.digest.XXHash32.update:90 ISTORE 4
org.apache.commons.codec.digest.XXHash32.update:92 ALOAD 0
org.apache.commons.codec.digest.XXHash32.update:92 GETFIELD org/apache/commons/codec/digest/XXHash32.pos I
org.apache.commons.codec.digest.XXHash32.update:92 ILOAD 3
org.apache.commons.codec.digest.XXHash32.update:92 IADD
org.apache.commons.codec.digest.XXHash32.update:92 BIPUSH 16
org.apache.commons.codec.digest.XXHash32.update:92 IF_ICMPGE L1 true false
org.apache.commons.codec.digest.XXHash32.update:105 ILOAD 4
org.apache.commons.codec.digest.XXHash32.update:105 BIPUSH 16
org.apache.commons.codec.digest.XXHash32.update:105 ISUB
org.apache.commons.codec.digest.XXHash32.update:105 ISTORE 5
org.apache.commons.codec.digest.XXHash32.update:106 ILOAD 2
org.apache.commons.codec.digest.XXHash32.update:106 ILOAD 5
org.apache.commons.codec.digest.XXHash32.update:106 IF_ICMPGT L4 false true
org.apache.commons.codec.digest.XXHash32.update:107 ALOAD 0
org.apache.commons.codec.digest.XXHash32.update:107 ALOAD 1
org.apache.commons.codec.digest.XXHash32.update:107 ILOAD 2
org.apache.commons.codec.digest.XXHash32.update:107 INVOKESPECIAL org/apache/commons/codec/digest/XXHash32.process([BI)V
org.apache.commons.codec.digest.XXHash32.update:108 IINC 2 16
org.apache.commons.codec.digest.XXHash32.getValue:120 ALOAD 0
org.apache.commons.codec.digest.XXHash32.getValue:120 GETFIELD org/apache/commons/codec/digest/XXHash32.totalLen I
org.apache.commons.codec.digest.XXHash32.getValue:120 BIPUSH 16
org.apache.commons.codec.digest.XXHash32.getValue:120 IF_ICMPLE L0 false true
org.apache.commons.codec.digest.XXHash32.getValue:121 ALOAD 0
org.apache.commons.codec.digest.XXHash32.getValue:121 GETFIELD org/apache/commons/codec/digest/XXHash32.state [I
org.apache.commons.codec.digest.XXHash32.getValue:121 ICONST_0
org.apache.commons.codec.digest.XXHash32.getValue:121 IALOAD
org.apache.commons.codec.digest.XXHash32.getValue:121 ICONST_1
org.apache.commons.codec.digest.XXHash32.getValue:121 INVOKESTATIC java/lang/Integer.rotateLeft(II)I
org.apache.commons.codec.digest.XXHash32.getValue:121 ALOAD 0
org.apache.commons.codec.digest.XXHash32.getValue:121 GETFIELD org/apache/commons/codec/digest/XXHash32.state [I
org.apache.commons.codec.digest.XXHash32.getValue:121 ICONST_1
org.apache.commons.codec.digest.XXHash32.getValue:121 IALOAD
org.apache.commons.codec.digest.XXHash32.getValue:121 BIPUSH 7
org.apache.commons.codec.digest.XXHash32.getValue:121 INVOKESTATIC java/lang/Integer.rotateLeft(II)I
org.apache.commons.codec.digest.XXHash32.getValue:121 IADD
org.apache.commons.codec.digest.XXHash32.getValue:121 ALOAD 0
org.apache.commons.codec.digest.XXHash32.getValue:121 GETFIELD org/apache/commons/codec/digest/XXHash32.state [I
org.apache.commons.codec.digest.XXHash32.getValue:121 ICONST_2
org.apache.commons.codec.digest.XXHash32.getValue:121 IALOAD
org.apache.commons.codec.digest.XXHash32.getValue:121 BIPUSH 12
org.apache.commons.codec.digest.XXHash32.getValue:121 INVOKESTATIC java/lang/Integer.rotateLeft(II)I
org.apache.commons.codec.digest.XXHash32.getValue:121 IADD
org.apache.commons.codec.digest.XXHash32.getValue:121 ALOAD 0
org.apache.commons.codec.digest.XXHash32.getValue:121 GETFIELD org/apache/commons/codec/digest/XXHash32.state [I
org.apache.commons.codec.digest.XXHash32.getValue:121 ICONST_3
org.apache.commons.codec.digest.XXHash32.getValue:121 IALOAD
org.apache.commons.codec.digest.XXHash32.getValue:121 BIPUSH 18
org.apache.commons.codec.digest.XXHash32.getValue:121 INVOKESTATIC java/lang/Integer.rotateLeft(II)I
org.apache.commons.codec.digest.XXHash32.getValue:121 IADD
org.apache.commons.codec.digest.XXHash32.getValue:121 ISTORE 1
org.apache.commons.codec.digest.XXHash32.getValue:129 ILOAD 1
org.apache.commons.codec.digest.XXHash32.getValue:129 ALOAD 0
org.apache.commons.codec.digest.XXHash32.getValue:129 GETFIELD org/apache/commons/codec/digest/XXHash32.totalLen I
org.apache.commons.codec.digest.XXHash32.getValue:129 IADD
org.apache.commons.codec.digest.XXHash32.getValue:129 ISTORE 1
org.apache.commons.codec.digest.XXHash32.getValue:131 ICONST_0
org.apache.commons.codec.digest.XXHash32.getValue:131 ISTORE 2
org.apache.commons.codec.digest.XXHash32.getValue:132 ALOAD 0
org.apache.commons.codec.digest.XXHash32.getValue:132 GETFIELD org/apache/commons/codec/digest/XXHash32.pos I
org.apache.commons.codec.digest.XXHash32.getValue:132 ICONST_4
org.apache.commons.codec.digest.XXHash32.getValue:132 ISUB
org.apache.commons.codec.digest.XXHash32.getValue:132 ISTORE 3
org.apache.commons.codec.digest.XXHash32.getValue:133 ILOAD 2
org.apache.commons.codec.digest.XXHash32.getValue:133 ILOAD 3
org.apache.commons.codec.digest.XXHash32.getValue:133 IF_ICMPGT L3 true false
org.apache.commons.codec.digest.XXHash32.getValue:136 ILOAD 2
org.apache.commons.codec.digest.XXHash32.getValue:136 ALOAD 0
org.apache.commons.codec.digest.XXHash32.getValue:136 GETFIELD org/apache/commons/codec/digest/XXHash32.pos I
org.apache.commons.codec.digest.XXHash32.getValue:136 IF_ICMPGE L4 true false
org.apache.commons.codec.digest.XXHash32.getValue:140 ILOAD 1
org.apache.commons.codec.digest.XXHash32.getValue:140 ILOAD 1
org.apache.commons.codec.digest.XXHash32.getValue:140 BIPUSH 15
org.apache.commons.codec.digest.XXHash32.getValue:140 IUSHR
org.apache.commons.codec.digest.XXHash32.getValue:140 IXOR
org.apache.commons.codec.digest.XXHash32.getValue:140 ISTORE 1
org.apache.commons.codec.digest.XXHash32.getValue:141 ILOAD 1
org.apache.commons.codec.digest.XXHash32.getValue:141 LDC -2048144777
org.apache.commons.codec.digest.XXHash32.getValue:141 IMUL
org.apache.commons.codec.digest.XXHash32.getValue:141 ISTORE 1
org.apache.commons.codec.digest.XXHash32.getValue:142 ILOAD 1
org.apache.commons.codec.digest.XXHash32.getValue:142 ILOAD 1
org.apache.commons.codec.digest.XXHash32.getValue:142 BIPUSH 13
org.apache.commons.codec.digest.XXHash32.getValue:142 IUSHR
org.apache.commons.codec.digest.XXHash32.getValue:142 IXOR
org.apache.commons.codec.digest.XXHash32.getValue:142 ISTORE 1
org.apache.commons.codec.digest.XXHash32.getValue:143 ILOAD 1
org.apache.commons.codec.digest.XXHash32.getValue:143 LDC -1028477379
org.apache.commons.codec.digest.XXHash32.getValue:143 IMUL
org.apache.commons.codec.digest.XXHash32.getValue:143 ISTORE 1
org.apache.commons.codec.digest.XXHash32.getValue:144 ILOAD 1
org.apache.commons.codec.digest.XXHash32.getValue:144 ILOAD 1
org.apache.commons.codec.digest.XXHash32.getValue:144 BIPUSH 16
org.apache.commons.codec.digest.XXHash32.getValue:144 IUSHR
org.apache.commons.codec.digest.XXHash32.getValue:144 IXOR
org.apache.commons.codec.digest.XXHash32.getValue:144 ISTORE 1
org.apache.commons.codec.digest.XXHash32.getValue:145 ILOAD 1
org.apache.commons.codec.digest.XXHash32.getValue:145 I2L
org.apache.commons.codec.digest.XXHash32.getValue:145 LDC 4294967295
org.apache.commons.codec.digest.XXHash32.getValue:145 LAND
org.apache.commons.codec.digest.XXHash32.getValue:145 LRETURN
org.apache.commons.codec.digest.XXHash32.getInt:149 ALOAD 0
org.apache.commons.codec.digest.XXHash32.getInt:149 ILOAD 1
org.apache.commons.codec.digest.XXHash32.getInt:149 ICONST_4
org.apache.commons.codec.digest.XXHash32.getInt:149 INVOKESTATIC org/apache/commons/codec/digest/XXHash32.fromLittleEndian([BII)J
org.apache.commons.codec.digest.XXHash32.getInt:149 LDC 4294967295
org.apache.commons.codec.digest.XXHash32.getInt:149 LAND
org.apache.commons.codec.digest.XXHash32.getInt:149 L2I
org.apache.commons.codec.digest.XXHash32.getInt:149 IRETURN
org.apache.commons.codec.digest.XXHash32.initializeState:153 ALOAD 0
org.apache.commons.codec.digest.XXHash32.initializeState:153 GETFIELD org/apache/commons/codec/digest/XXHash32.state [I
org.apache.commons.codec.digest.XXHash32.initializeState:153 ICONST_0
org.apache.commons.codec.digest.XXHash32.initializeState:153 ALOAD 0
org.apache.commons.codec.digest.XXHash32.initializeState:153 GETFIELD org/apache/commons/codec/digest/XXHash32.seed I
org.apache.commons.codec.digest.XXHash32.initializeState:153 LDC -1640531535
org.apache.commons.codec.digest.XXHash32.initializeState:153 IADD
org.apache.commons.codec.digest.XXHash32.initializeState:153 LDC -2048144777
org.apache.commons.codec.digest.XXHash32.initializeState:153 IADD
org.apache.commons.codec.digest.XXHash32.initializeState:153 IASTORE
org.apache.commons.codec.digest.XXHash32.initializeState:154 ALOAD 0
org.apache.commons.codec.digest.XXHash32.initializeState:154 GETFIELD org/apache/commons/codec/digest/XXHash32.state [I
org.apache.commons.codec.digest.XXHash32.initializeState:154 ICONST_1
org.apache.commons.codec.digest.XXHash32.initializeState:154 ALOAD 0
org.apache.commons.codec.digest.XXHash32.initializeState:154 GETFIELD org/apache/commons/codec/digest/XXHash32.seed I
org.apache.commons.codec.digest.XXHash32.initializeState:154 LDC -2048144777
org.apache.commons.codec.digest.XXHash32.initializeState:154 IADD
org.apache.commons.codec.digest.XXHash32.initializeState:154 IASTORE
org.apache.commons.codec.digest.XXHash32.initializeState:155 ALOAD 0
org.apache.commons.codec.digest.XXHash32.initializeState:155 GETFIELD org/apache/commons/codec/digest/XXHash32.state [I
org.apache.commons.codec.digest.XXHash32.initializeState:155 ICONST_2
org.apache.commons.codec.digest.XXHash32.initializeState:155 ALOAD 0
org.apache.commons.codec.digest.XXHash32.initializeState:155 GETFIELD org/apache/commons/codec/digest/XXHash32.seed I
org.apache.commons.codec.digest.XXHash32.initializeState:155 IASTORE
org.apache.commons.codec.digest.XXHash32.initializeState:156 ALOAD 0
org.apache.commons.codec.digest.XXHash32.initializeState:156 GETFIELD org/apache/commons/codec/digest/XXHash32.state [I
org.apache.commons.codec.digest.XXHash32.initializeState:156 ICONST_3
org.apache.commons.codec.digest.XXHash32.initializeState:156 ALOAD 0
org.apache.commons.codec.digest.XXHash32.initializeState:156 GETFIELD org/apache/commons/codec/digest/XXHash32.seed I
org.apache.commons.codec.digest.XXHash32.initializeState:156 LDC -1640531535
org.apache.commons.codec.digest.XXHash32.initializeState:156 ISUB
org.apache.commons.codec.digest.XXHash32.initializeState:156 IASTORE
org.apache.commons.codec.digest.XXHash32.process:161 ALOAD 0
org.apache.commons.codec.digest.XXHash32.process:161 GETFIELD org/apache/commons/codec/digest/XXHash32.state [I
org.apache.commons.codec.digest.XXHash32.process:161 ICONST_0
org.apache.commons.codec.digest.XXHash32.process:161 IALOAD
org.apache.commons.codec.digest.XXHash32.process:161 ISTORE 3
org.apache.commons.codec.digest.XXHash32.process:162 ALOAD 0
org.apache.commons.codec.digest.XXHash32.process:162 GETFIELD org/apache/commons/codec/digest/XXHash32.state [I
org.apache.commons.codec.digest.XXHash32.process:162 ICONST_1
org.apache.commons.codec.digest.XXHash32.process:162 IALOAD
org.apache.commons.codec.digest.XXHash32.process:162 ISTORE 4
org.apache.commons.codec.digest.XXHash32.process:163 ALOAD 0
org.apache.commons.codec.digest.XXHash32.process:163 GETFIELD org/apache/commons/codec/digest/XXHash32.state [I
org.apache.commons.codec.digest.XXHash32.process:163 ICONST_2
org.apache.commons.codec.digest.XXHash32.process:163 IALOAD
org.apache.commons.codec.digest.XXHash32.process:163 ISTORE 5
org.apache.commons.codec.digest.XXHash32.process:164 ALOAD 0
org.apache.commons.codec.digest.XXHash32.process:164 GETFIELD org/apache/commons/codec/digest/XXHash32.state [I
org.apache.commons.codec.digest.XXHash32.process:164 ICONST_3
org.apache.commons.codec.digest.XXHash32.process:164 IALOAD
org.apache.commons.codec.digest.XXHash32.process:164 ISTORE 6
org.apache.commons.codec.digest.XXHash32.process:166 ILOAD 3
org.apache.commons.codec.digest.XXHash32.process:166 ALOAD 1
org.apache.commons.codec.digest.XXHash32.process:166 ILOAD 2
org.apache.commons.codec.digest.XXHash32.process:166 INVOKESTATIC org/apache/commons/codec/digest/XXHash32.getInt([BI)I
org.apache.commons.codec.digest.XXHash32.process:166 LDC -2048144777
org.apache.commons.codec.digest.XXHash32.process:166 IMUL
org.apache.commons.codec.digest.XXHash32.process:166 IADD
org.apache.commons.codec.digest.XXHash32.process:166 BIPUSH 13
org.apache.commons.codec.digest.XXHash32.process:166 INVOKESTATIC java/lang/Integer.rotateLeft(II)I
org.apache.commons.codec.digest.XXHash32.process:166 LDC -1640531535
org.apache.commons.codec.digest.XXHash32.process:166 IMUL
org.apache.commons.codec.digest.XXHash32.process:166 ISTORE 3
org.apache.commons.codec.digest.XXHash32.process:167 ILOAD 4
org.apache.commons.codec.digest.XXHash32.process:167 ALOAD 1
org.apache.commons.codec.digest.XXHash32.process:167 ILOAD 2
org.apache.commons.codec.digest.XXHash32.process:167 ICONST_4
org.apache.commons.codec.digest.XXHash32.process:167 IADD
org.apache.commons.codec.digest.XXHash32.process:167 INVOKESTATIC org/apache/commons/codec/digest/XXHash32.getInt([BI)I
org.apache.commons.codec.digest.XXHash32.process:167 LDC -2048144777
org.apache.commons.codec.digest.XXHash32.process:167 IMUL
org.apache.commons.codec.digest.XXHash32.process:167 IADD
org.apache.commons.codec.digest.XXHash32.process:167 BIPUSH 13
org.apache.commons.codec.digest.XXHash32.process:167 INVOKESTATIC java/lang/Integer.rotateLeft(II)I
org.apache.commons.codec.digest.XXHash32.process:167 LDC -1640531535
org.apache.commons.codec.digest.XXHash32.process:167 IMUL
org.apache.commons.codec.digest.XXHash32.process:167 ISTORE 4
org.apache.commons.codec.digest.XXHash32.process:168 ILOAD 5
org.apache.commons.codec.digest.XXHash32.process:168 ALOAD 1
org.apache.commons.codec.digest.XXHash32.process:168 ILOAD 2
org.apache.commons.codec.digest.XXHash32.process:168 BIPUSH 8
org.apache.commons.codec.digest.XXHash32.process:168 IADD
org.apache.commons.codec.digest.XXHash32.process:168 INVOKESTATIC org/apache/commons/codec/digest/XXHash32.getInt([BI)I
org.apache.commons.codec.digest.XXHash32.process:168 LDC -2048144777
org.apache.commons.codec.digest.XXHash32.process:168 IMUL
org.apache.commons.codec.digest.XXHash32.process:168 IADD
org.apache.commons.codec.digest.XXHash32.process:168 BIPUSH 13
org.apache.commons.codec.digest.XXHash32.process:168 INVOKESTATIC java/lang/Integer.rotateLeft(II)I
org.apache.commons.codec.digest.XXHash32.process:168 LDC -1640531535
org.apache.commons.codec.digest.XXHash32.process:168 IMUL
org.apache.commons.codec.digest.XXHash32.process:168 ISTORE 5
org.apache.commons.codec.digest.XXHash32.process:169 ILOAD 6
org.apache.commons.codec.digest.XXHash32.process:169 ALOAD 1
org.apache.commons.codec.digest.XXHash32.process:169 ILOAD 2
org.apache.commons.codec.digest.XXHash32.process:169 BIPUSH 12
org.apache.commons.codec.digest.XXHash32.process:169 IADD
org.apache.commons.codec.digest.XXHash32.process:169 INVOKESTATIC org/apache/commons/codec/digest/XXHash32.getInt([BI)I
org.apache.commons.codec.digest.XXHash32.process:169 LDC -2048144777
org.apache.commons.codec.digest.XXHash32.process:169 IMUL
org.apache.commons.codec.digest.XXHash32.process:169 IADD
org.apache.commons.codec.digest.XXHash32.process:169 BIPUSH 13
org.apache.commons.codec.digest.XXHash32.process:169 INVOKESTATIC java/lang/Integer.rotateLeft(II)I
org.apache.commons.codec.digest.XXHash32.process:169 LDC -1640531535
org.apache.commons.codec.digest.XXHash32.process:169 IMUL
org.apache.commons.codec.digest.XXHash32.process:169 ISTORE 6
org.apache.commons.codec.digest.XXHash32.process:171 ALOAD 0
org.apache.commons.codec.digest.XXHash32.process:171 GETFIELD org/apache/commons/codec/digest/XXHash32.state [I
org.apache.commons.codec.digest.XXHash32.process:171 ICONST_0
org.apache.commons.codec.digest.XXHash32.process:171 ILOAD 3
org.apache.commons.codec.digest.XXHash32.process:171 IASTORE
org.apache.commons.codec.digest.XXHash32.process:172 ALOAD 0
org.apache.commons.codec.digest.XXHash32.process:172 GETFIELD org/apache/commons/codec/digest/XXHash32.state [I
org.apache.commons.codec.digest.XXHash32.process:172 ICONST_1
org.apache.commons.codec.digest.XXHash32.process:172 ILOAD 4
org.apache.commons.codec.digest.XXHash32.process:172 IASTORE
org.apache.commons.codec.digest.XXHash32.process:173 ALOAD 0
org.apache.commons.codec.digest.XXHash32.process:173 GETFIELD org/apache/commons/codec/digest/XXHash32.state [I
org.apache.commons.codec.digest.XXHash32.process:173 ICONST_2
org.apache.commons.codec.digest.XXHash32.process:173 ILOAD 5
org.apache.commons.codec.digest.XXHash32.process:173 IASTORE
org.apache.commons.codec.digest.XXHash32.process:174 ALOAD 0
org.apache.commons.codec.digest.XXHash32.process:174 GETFIELD org/apache/commons/codec/digest/XXHash32.state [I
org.apache.commons.codec.digest.XXHash32.process:174 ICONST_3
org.apache.commons.codec.digest.XXHash32.process:174 ILOAD 6
org.apache.commons.codec.digest.XXHash32.process:174 IASTORE
org.apache.commons.codec.digest.XXHash32.process:176 ALOAD 0
org.apache.commons.codec.digest.XXHash32.process:176 ICONST_0
org.apache.commons.codec.digest.XXHash32.process:176 PUTFIELD org/apache/commons/codec/digest/XXHash32.pos I
org.apache.commons.codec.digest.XXHash32.fromLittleEndian:191 LCONST_0
org.apache.commons.codec.digest.XXHash32.fromLittleEndian:191 LSTORE 3
org.apache.commons.codec.digest.XXHash32.fromLittleEndian:192 ICONST_0
org.apache.commons.codec.digest.XXHash32.fromLittleEndian:192 ISTORE 5
org.apache.commons.codec.digest.XXHash32.fromLittleEndian:192 ILOAD 5
org.apache.commons.codec.digest.XXHash32.fromLittleEndian:192 ILOAD 2
org.apache.commons.codec.digest.XXHash32.fromLittleEndian:192 IF_ICMPGE L2 true true
org.apache.commons.codec.digest.XXHash32.fromLittleEndian:192 IINC 5 1
org.apache.commons.codec.digest.XXHash32.fromLittleEndian:193 LLOAD 3
org.apache.commons.codec.digest.XXHash32.fromLittleEndian:193 ALOAD 0
org.apache.commons.codec.digest.XXHash32.fromLittleEndian:193 ILOAD 1
org.apache.commons.codec.digest.XXHash32.fromLittleEndian:193 ILOAD 5
org.apache.commons.codec.digest.XXHash32.fromLittleEndian:193 IADD
org.apache.commons.codec.digest.XXHash32.fromLittleEndian:193 BALOAD
org.apache.commons.codec.digest.XXHash32.fromLittleEndian:193 I2L
org.apache.commons.codec.digest.XXHash32.fromLittleEndian:193 LDC 255
org.apache.commons.codec.digest.XXHash32.fromLittleEndian:193 LAND
org.apache.commons.codec.digest.XXHash32.fromLittleEndian:193 BIPUSH 8
org.apache.commons.codec.digest.XXHash32.fromLittleEndian:193 ILOAD 5
org.apache.commons.codec.digest.XXHash32.fromLittleEndian:193 IMUL
org.apache.commons.codec.digest.XXHash32.fromLittleEndian:193 LSHL
org.apache.commons.codec.digest.XXHash32.fromLittleEndian:193 LOR
org.apache.commons.codec.digest.XXHash32.fromLittleEndian:193 LSTORE 3
org.apache.commons.codec.digest.XXHash32.fromLittleEndian:195 LLOAD 3
org.apache.commons.codec.digest.XXHash32.fromLittleEndian:195 LRETURN
org.apache.commons.codec.digest.XXHash32Test.<init>:52 INVOKEVIRTUAL java/net/URL.toURI()Ljava/net/URI;
org.apache.commons.codec.digest.XXHash32Test.<init>:52 ASTORE 4
org.apache.commons.codec.digest.XXHash32Test.<init>:56 ALOAD 0
org.apache.commons.codec.digest.XXHash32Test.<init>:56 NEW java/io/File
org.apache.commons.codec.digest.XXHash32Test.<init>:56 DUP
org.apache.commons.codec.digest.XXHash32Test.<init>:56 ALOAD 4
org.apache.commons.codec.digest.XXHash32Test.<init>:56 INVOKESPECIAL java/io/File.<init>(Ljava/net/URI;)V
org.apache.commons.codec.digest.XXHash32Test.<init>:56 PUTFIELD org/apache/commons/codec/digest/XXHash32Test.file Ljava/io/File;
org.apache.commons.codec.digest.XXHash32Test.<init>:57 ALOAD 0
org.apache.commons.codec.digest.XXHash32Test.<init>:57 ALOAD 2
org.apache.commons.codec.digest.XXHash32Test.<init>:57 PUTFIELD org/apache/commons/codec/digest/XXHash32Test.expectedChecksum Ljava/lang/String;
org.apache.commons.codec.digest.XXHash32Test.verifyChecksum:71 NEW org/apache/commons/codec/digest/XXHash32
org.apache.commons.codec.digest.XXHash32Test.verifyChecksum:71 DUP
org.apache.commons.codec.digest.XXHash32Test.verifyChecksum:71 INVOKESPECIAL org/apache/commons/codec/digest/XXHash32.<init>()V
org.apache.commons.codec.digest.XXHash32Test.verifyChecksum:71 ASTORE 1
org.apache.commons.codec.digest.XXHash32Test.verifyChecksum:72 NEW java/io/FileInputStream
org.apache.commons.codec.digest.XXHash32Test.verifyChecksum:72 ASTORE 2
org.apache.commons.codec.digest.XXHash32Test.verifyChecksum:73 ALOAD 2
org.apache.commons.codec.digest.XXHash32Test.verifyChecksum:73 INVOKESTATIC org/apache/commons/codec/digest/XXHash32Test.toByteArray(Ljava/io/InputStream;)[B
org.apache.commons.codec.digest.XXHash32Test.verifyChecksum:73 ASTORE 4
org.apache.commons.codec.digest.XXHash32Test.verifyChecksum:74 ALOAD 1
org.apache.commons.codec.digest.XXHash32Test.verifyChecksum:74 ALOAD 4
org.apache.commons.codec.digest.XXHash32Test.verifyChecksum:74 ICONST_0
org.apache.commons.codec.digest.XXHash32Test.verifyChecksum:74 ALOAD 4
org.apache.commons.codec.digest.XXHash32Test.verifyChecksum:74 ARRAYLENGTH
org.apache.commons.codec.digest.XXHash32Test.verifyChecksum:74 INVOKEVIRTUAL org/apache/commons/codec/digest/XXHash32.update([BII)V
org.apache.commons.codec.digest.XXHash32Test.verifyChecksum:76 NEW java/lang/StringBuilder
org.apache.commons.codec.digest.XXHash32Test.verifyChecksum:76 DUP
org.apache.commons.codec.digest.XXHash32Test.verifyChecksum:76 INVOKESPECIAL java/lang/StringBuilder.<init>()V
org.apache.commons.codec.digest.XXHash32Test.verifyChecksum:76 LDC "checksum for "
org.apache.commons.codec.digest.XXHash32Test.verifyChecksum:76 INVOKEVIRTUAL java/lang/StringBuilder.append(Ljava/lang/String;)Ljava/lang/StringBuilder;
org.apache.commons.codec.digest.XXHash32Test.verifyChecksum:76 ALOAD 0
org.apache.commons.codec.digest.XXHash32Test.verifyChecksum:76 GETFIELD org/apache/commons/codec/digest/XXHash32Test.file Ljava/io/File;
org.apache.commons.codec.digest.XXHash32Test.verifyChecksum:76 INVOKEVIRTUAL java/io/File.getName()Ljava/lang/String;
org.apache.commons.codec.digest.XXHash32Test.verifyChecksum:76 INVOKEVIRTUAL java/lang/StringBuilder.append(Ljava/lang/String;)Ljava/lang/StringBuilder;
org.apache.commons.codec.digest.XXHash32Test.verifyChecksum:76 INVOKEVIRTUAL java/lang/StringBuilder.toString()Ljava/lang/String;
org.apache.commons.codec.digest.XXHash32Test.verifyChecksum:76 ALOAD 0
org.apache.commons.codec.digest.XXHash32Test.verifyChecksum:76 GETFIELD org/apache/commons/codec/digest/XXHash32Test.expectedChecksum Ljava/lang/String;
org.apache.commons.codec.digest.XXHash32Test.verifyChecksum:76 ALOAD 1
org.apache.commons.codec.digest.XXHash32Test.verifyChecksum:76 INVOKEVIRTUAL org/apache/commons/codec/digest/XXHash32.getValue()J
org.apache.commons.codec.digest.XXHash32Test.verifyChecksum:76 INVOKESTATIC java/lang/Long.toHexString(J)Ljava/lang/String;
org.apache.commons.codec.digest.XXHash32Test.verifyChecksum:76 INVOKESTATIC org/junit/Assert.assertEquals(Ljava/lang/String;Ljava/lang/Object;Ljava/lang/Object;)V
org.apache.commons.codec.digest.XXHash32Test.toByteArray:80 NEW java/io/ByteArrayOutputStream
org.apache.commons.codec.digest.XXHash32Test.toByteArray:80 DUP
org.apache.commons.codec.digest.XXHash32Test.toByteArray:80 INVOKESPECIAL java/io/ByteArrayOutputStream.<init>()V
org.apache.commons.codec.digest.XXHash32Test.toByteArray:80 ASTORE 1
org.apache.commons.codec.digest.XXHash32Test.toByteArray:81 ALOAD 0
org.apache.commons.codec.digest.XXHash32Test.toByteArray:81 ALOAD 1
org.apache.commons.codec.digest.XXHash32Test.toByteArray:81 SIPUSH 10240
org.apache.commons.codec.digest.XXHash32Test.toByteArray:81 INVOKESTATIC org/apache/commons/codec/digest/XXHash32Test.copy(Ljava/io/InputStream;Ljava/io/OutputStream;I)J
org.apache.commons.codec.digest.XXHash32Test.toByteArray:82 ALOAD 1
org.apache.commons.codec.digest.XXHash32Test.toByteArray:82 INVOKEVIRTUAL java/io/ByteArrayOutputStream.toByteArray()[B
org.apache.commons.codec.digest.XXHash32Test.toByteArray:82 ARETURN
org.apache.commons.codec.digest.XXHash32Test.copy:86 ILOAD 2
org.apache.commons.codec.digest.XXHash32Test.copy:86 NEWARRAY T_BYTE
org.apache.commons.codec.digest.XXHash32Test.copy:86 ASTORE 3
org.apache.commons.codec.digest.XXHash32Test.copy:89 ICONST_M1
org.apache.commons.codec.digest.XXHash32Test.copy:89 ALOAD 0
org.apache.commons.codec.digest.XXHash32Test.copy:89 ALOAD 3
org.apache.commons.codec.digest.XXHash32Test.copy:89 INVOKEVIRTUAL java/io/InputStream.read([B)I
org.apache.commons.codec.digest.XXHash32Test.copy:89 DUP
org.apache.commons.codec.digest.XXHash32Test.copy:89 ISTORE 4
org.apache.commons.codec.digest.XXHash32Test.copy:89 IF_ICMPEQ L1 false true
org.apache.commons.codec.digest.XXHash32Test.copy:90 ALOAD 1
org.apache.commons.codec.digest.XXHash32Test.copy:90 ILOAD 4
org.apache.commons.codec.digest.XXHash32Test.copy:90 INVOKEVIRTUAL java/io/OutputStream.write([BII)V

Slice consists of 7158 bytecode instructions.
Computation took 9.39 seconds.
